greyhorse_es/__init__.py
greyhorse_es/config.py
greyhorse_es/containers.py
greyhorse_es/contexts.py
greyhorse_es/engine.py
greyhorse_es/factory.py
greyhorse_es/resources.py
greyhorse_es/translations.toml
greyhorse_es-0.1.dist-info/METADATA
greyhorse_es-0.1.dist-info/WHEEL
greyhorse_es-0.1.dist-info/RECORD
